AUTHORS
CHANGELOG.txt
DESCRIPTION
LICENSE
MANIFEST.in
setup.py
django_good_practice_examples.egg-info/PKG-INFO
django_good_practice_examples.egg-info/SOURCES.txt
django_good_practice_examples.egg-info/dependency_links.txt
django_good_practice_examples.egg-info/requires.txt
django_good_practice_examples.egg-info/top_level.txt
good_practice_examples/__init__.py
good_practice_examples/admin.py
good_practice_examples/cms_app.py
good_practice_examples/models.py
good_practice_examples/urls.py
good_practice_examples/views.py
good_practice_examples/migrations/0001_initial.py
good_practice_examples/migrations/0002_change_slot_for_description_placeholders.py
good_practice_examples/migrations/0003_auto__del_field_sectortranslation_sector__del_field_sectortranslation_.py
good_practice_examples/migrations/0004_auto__add_field_goodpracticeexample_practice_description.py
good_practice_examples/migrations/0005_migrate_placeholder.py
good_practice_examples/migrations/0006_auto.py
good_practice_examples/migrations/__init__.py
good_practice_examples/templates/good_practice_examples/examples_list.html
good_practice_examples/templates/good_practice_examples/partials/example_item.html
good_practice_examples/tests/__init__.py
good_practice_examples/tests/factories.py
good_practice_examples/tests/models_tests.py
good_practice_examples/tests/runtests.py
good_practice_examples/tests/south_settings.py
good_practice_examples/tests/test_settings.py
good_practice_examples/tests/urls.py
good_practice_examples/tests/integration_tests/__init__.py
good_practice_examples/tests/integration_tests/views_tests.py
good_practice_examples/tests/test_app/__init__.py
good_practice_examples/tests/test_app/models.py
good_practice_examples/tests/test_app/templates/base.html
good_practice_examples/tests/test_app/templates/standard.html