Metadata-Version: 1.0
Name: django-good-practice-examples
Version: 1.0
Summary: An app for managing and displaying good practice examples for different
